bugcatcher/__init__.py
bugcatcher/ftl.py
bugcatcher-0.1.9.dist-info/LICENSE
bugcatcher-0.1.9.dist-info/METADATA
bugcatcher-0.1.9.dist-info/WHEEL
bugcatcher-0.1.9.dist-info/entry_points.txt
bugcatcher-0.1.9.dist-info/top_level.txt
bugcatcher-0.1.9.dist-info/RECORD
