Metadata-Version: 2.1
Name: bugcatcher
Version: 0.1.9
Summary: Faster Than Light Command Line Test Client
Home-page: https://github.com/faster-than-light/bugcatcher
Author: Faster Than Light
Author-email: devops@fasterthanlight.dev
Maintainer: Faster Than Light
Maintainer-email: devops@fasterthanlight.dev
License: GNU GPL v2.0
Platform: UNKNOWN
Classifier: Development Status :: 4 - Beta
Classifier: Framework :: Pytest
Classifier: Intended Audience :: Developers
Classifier: Topic :: Software Development :: Testing
Classifier: Programming Language :: Python
Classifier: Programming Language :: Python :: 3.5
Classifier: Programming Language :: Python :: 3.6
Classifier: Programming Language :: Python :: 3.7
Classifier: Programming Language :: Python :: Implementation :: CPython
Classifier: Programming Language :: Python :: Implementation :: PyPy
Classifier: Operating System :: OS Independent
Classifier: License :: OSI Approved :: GNU General Public License v2 (GPLv2)
Requires-Python: >=3.4
Requires-Dist: gitpython
Requires-Dist: requests
Requires-Dist: colorama
Requires-Dist: pytest (>=3.5.0)
